{
  "palette": [
    {
      "char": "r",
      "block": "minecraft:cyan_terracotta",
      "damaged": "minecraft:iron_bars"
    },
    {
      "char": "t",
      "block": "minecraft:black_concrete",
      "damaged": "minecraft:iron_bars"
    },
    {
      "char": "T",
      "block": "minecraft:dirt"
    },
    {
      "char": "]",
      "block": "connectedglass:borderless_glass"
    },
    {
      "char": "⇊",
      "block": "minecraft:chest[facing=south]",
      "loot": "chestloot"
    },
    {
      "char": "⇈",
      "block": "minecraft:chest[facing=north]",
      "loot": "chestloot"
    },
    {
      "char": "⇇",
      "block": "minecraft:chest[facing=west]",
      "loot": "chestloot"
    },
    {
      "char": "⇉",
      "block": "minecraft:chest[facing=east]",
      "loot": "chestloot"
    },


    {
      "char": "w",
      "block": "minecraft:polished_blackstone_brick_wall"
    },

    {
      "char": "R",
      "block": "minecraft:cyan_terracotta",
      "damaged": "minecraft:iron_bars"
    },
    {
      "char": ";",
      "block": "minecraft:furnace",
      "damaged": "minecraft:iron_bars",
      "tag": {
        "Items": [
          {
            "Slot": 0,
            "id": "minecraft:coal",
            "Count": 10
          }
        ]
      }
    },
    {
      "char": "Q",
      "block": "minecraft:quartz_block",
      "damaged": "minecraft:iron_bars"
    },
    {
      "char": "u",
      "block": "minecraft:smooth_stone_slab[type=double]",
      "damaged": "minecraft:iron_bars"
    },
    {
      "char": "b",
      "block": "minecraft:structure_void"
    },
    {
      "char": "B",
      "block": "minecraft:bricks",
      "damaged": "minecraft:iron_bars"
    },
    {
      "char": "v",
      "variant": "stonebrick",
      "damaged": "minecraft:iron_bars"
    },
    {
      "char": "y",
      "variant": "stonebrick",
      "damaged": "minecraft:iron_bars"
    },
    {
      "char": "x",
      "variant": "stonebrick",
      "damaged": "minecraft:iron_bars"
    },
    {
      "char": "A",
      "block": "minecraft:stone_brick_stairs[facing=west,half=bottom,shape=straight]"
    },
    {
      "char": "z",
      "block": "minecraft:stone_brick_stairs[facing=north,half=bottom,shape=straight]"
    },
    {
      "char": "c",
      "block": "minecraft:stone_brick_stairs[facing=south,half=bottom,shape=straight]"
    },
    {
      "char": "d",
      "block": "minecraft:stone_brick_stairs[facing=north,half=top,shape=straight]"
    },
    {
      "char": "(",
      "block": "minecraft:quartz_stairs[facing=north,half=bottom,shape=straight]"
    },
    {
      "char": ")",
      "block": "minecraft:quartz_stairs[facing=south,half=bottom,shape=straight]"
    },
    {
      "char": "/",
      "block": "minecraft:stone_stairs[facing=west,half=bottom,shape=straight]"
    },

    {
      "char": "u",
      "block": "minecraft:white_concrete"
    },
    {
      "char": "R",
      "block": "pneumaticcraft:smooth_plastic_brick_black"
    },
    {
      "char": "v",
      "block": "minecraft:black_concrete"
    },
    {
      "char": "U",
      "block": "absentbydesign:wall_obsidian"
    },
    {
      "char": "V",
      "block": "minecraft:obsidian"
    }
  ]
}